sankaku/__init__.py
sankaku/constants.py
sankaku/errors.py
sankaku/typedefs.py
sankaku/types.py
sankaku/utils.py
sankaku/clients/__init__.py
sankaku/clients/abc.py
sankaku/clients/clients.py
sankaku/clients/http_client.py
sankaku/models/__init__.py
sankaku/models/base.py
sankaku/models/books.py
sankaku/models/http.py
sankaku/models/pages.py
sankaku/models/posts.py
sankaku/models/tags.py
sankaku/models/users.py
sankaku/paginators/__init__.py
sankaku/paginators/abc.py
sankaku/paginators/paginators.py
sankaku-2.0.1.dist-info/LICENSE
sankaku-2.0.1.dist-info/METADATA
sankaku-2.0.1.dist-info/WHEEL
sankaku-2.0.1.dist-info/top_level.txt
sankaku-2.0.1.dist-info/RECORD
