Metadata-Version: 2.1
Name: sankaku
Version: 2.0.1
Summary: Asynchronous API wrapper for Sankaku Complex.
Home-page: https://github.com/zerex290/sankaku
Author: zerex290
Author-email: zerex290@gmail.com
License: MIT
Project-URL: Issue Tracker, https://github.com/zerex290/sankaku/issues
Keywords: sankaku,sankakucomplex,api
Platform: UNKNOWN
Classifier: Programming Language :: Python :: 3.8
Classifier: Programming Language :: Python :: 3.9
Classifier: Programming Language :: Python :: 3.10
Classifier: Programming Language :: Python :: 3.11
Classifier: License :: OSI Approved :: MIT License
Classifier: Operating System :: OS Independent
Requires-Python: >=3.8
License-File: LICENSE
Requires-Dist: aiohttp
Requires-Dist: aiohttp-retry
Requires-Dist: loguru
Requires-Dist: pydantic
Requires-Dist: typing-extensions ; python_version < "3.10"
Provides-Extra: dev
Requires-Dist: pyright ~=1.1.320 ; extra == 'dev'
Requires-Dist: pytest-asyncio ~=0.21.0 ; extra == 'dev'
Requires-Dist: pytest-cov ~=4.0.0 ; extra == 'dev'
Requires-Dist: pytest ~=7.3.1 ; extra == 'dev'
Requires-Dist: ruff ~=0.0.282 ; extra == 'dev'
Requires-Dist: yapf ~=0.40.1 ; extra == 'dev'
Provides-Extra: docs
Requires-Dist: mkdocs ; extra == 'docs'
Requires-Dist: mkdocs-material ; extra == 'docs'
Requires-Dist: mkdocstrings ; extra == 'docs'
Requires-Dist: mkdocstrings[python] ; extra == 'docs'
Provides-Extra: socks
Requires-Dist: aiohttp-socks ; extra == 'socks'
